typus/__init__.py
typus/constants.py
typus/export_schemas.py
typus/models/__init__.py
typus/models/clade.py
typus/models/classification.py
typus/models/detection.py
typus/models/geo.py
typus/models/geometry.py
typus/models/lineage.py
typus/models/serialise.py
typus/models/taxon.py
typus/models/tracks.py
typus/models/detection_utils/__init__.py
typus/models/detection_utils/utils.py
typus/ops/__init__.py
typus/ops/bbox.py
typus/ops/tracks.py
typus/orm/base.py
typus/orm/expanded_taxa.py
typus/schemas/BBox.json
typus/schemas/BBoxXYWHNorm.json
typus/schemas/Clade.json
typus/schemas/Detection.json
typus/schemas/EncodedMask.json
typus/schemas/HierarchicalClassificationResult.json
typus/schemas/ImageDetectionResult.json
typus/schemas/InstancePrediction.json
typus/schemas/LineageMap.json
typus/schemas/Taxon.json
typus/schemas/Track.json
typus/schemas/TrackStats.json
typus/services/__init__.py
typus/services/pg_index_helper.py
typus/services/projections.py
typus/services/sqlite_loader.py
typus/services/elevation/__init__.py
typus/services/elevation/postgres.py
typus/services/taxonomy/__init__.py
typus/services/taxonomy/abstract.py
typus/services/taxonomy/postgres.py
typus/services/taxonomy/sqlite.py
polli_typus-0.4.1.dist-info/METADATA
polli_typus-0.4.1.dist-info/WHEEL
polli_typus-0.4.1.dist-info/entry_points.txt
polli_typus-0.4.1.dist-info/licenses/LICENSE
polli_typus-0.4.1.dist-info/RECORD
