Metadata-Version: 2.4
Name: polli-typus
Version: 0.4.1
Summary: Taxonomic types, projections and async taxonomy services for Polli-Labs.
Project-URL: Homepage, https://github.com/polli-labs/typus
Project-URL: Issues, https://github.com/polli-labs/typus/issues
Author-email: Polli-Labs <caleb@polli.ai>
License-Expression: MIT
License-File: LICENSE
Keywords: ecology,pydantic,sqlalchemy,taxonomy
Classifier: Development Status :: 3 - Alpha
Classifier: Intended Audience :: Science/Research
Classifier: License :: OSI Approved :: MIT License
Classifier: Programming Language :: Python :: 3
Classifier: Programming Language :: Python :: 3 :: Only
Classifier: Programming Language :: Python :: 3.10
Classifier: Programming Language :: Python :: 3.11
Classifier: Programming Language :: Python :: 3.12
Classifier: Topic :: Scientific/Engineering :: Information Analysis
Requires-Python: >=3.10
Requires-Dist: pandas<3,>=2.0
Requires-Dist: polars<2,>=0.20
Requires-Dist: pydantic<3,>=2.7
Requires-Dist: rapidfuzz<4,>=3.6
Requires-Dist: requests<4,>=2.32
Requires-Dist: sqlalchemy[asyncio]<3,>=2.0
Provides-Extra: dev
Requires-Dist: aiosqlite>=0.19; extra == 'dev'
Requires-Dist: asyncpg>=0.29; extra == 'dev'
Requires-Dist: mkdocs-material<10,>=9.5; extra == 'dev'
Requires-Dist: mkdocs<2,>=1.6; extra == 'dev'
Requires-Dist: pre-commit>=3.7; extra == 'dev'
Requires-Dist: pyarrow<17,>=16; extra == 'dev'
Requires-Dist: pytest-asyncio>=0.23; extra == 'dev'
Requires-Dist: pytest-httpserver>=1.0; extra == 'dev'
Requires-Dist: pytest>=8.2; extra == 'dev'
Requires-Dist: ruff==0.4.4; extra == 'dev'
Requires-Dist: tqdm>=4.66; extra == 'dev'
Provides-Extra: docs
Requires-Dist: mkdocs-material<10,>=9.5; extra == 'docs'
Requires-Dist: mkdocs<2,>=1.6; extra == 'docs'
Requires-Dist: mkdocstrings-python<2,>=1.10; extra == 'docs'
Requires-Dist: mkdocstrings<1,>=0.24; extra == 'docs'
Provides-Extra: pgvector
Requires-Dist: psycopg-binary>=3.1; extra == 'pgvector'
Provides-Extra: postgres
Requires-Dist: asyncpg>=0.29; extra == 'postgres'
Provides-Extra: sqlite
Requires-Dist: aiosqlite>=0.19; extra == 'sqlite'
